{
  "/set/free-svg-backgrounds-and-patterns/": {
    "title": "Free SVG Backgrounds and Patterns",
    "patterns": []
  },
  "/set/three-dimensional-patterns/": {
    "title": "3D Patterns",
    "patterns": []
  },
  "/set/alternating-geometric-patterns/": {
    "title": "Alternating Geometric Patterns",
    "patterns": []
  },
  "/set/colorful-geometric-patterns/": {
    "title": "Colorful Geometric Patterns",
    "patterns": []
  },
  "/set/hotel-wall-patterns/": {
    "title": "Hotel Wall Patterns",
    "patterns": []
  }
}